emoji_lib/__init__.py
emoji_lib/core.py
my_text_emojifier-0.1.0.dist-info/licenses/LICENSE
my_text_emojifier-0.1.0.dist-info/METADATA
my_text_emojifier-0.1.0.dist-info/WHEEL
my_text_emojifier-0.1.0.dist-info/top_level.txt
my_text_emojifier-0.1.0.dist-info/RECORD
